README.md
setup.py
geneformer.egg-info/PKG-INFO
geneformer.egg-info/SOURCES.txt
geneformer.egg-info/dependency_links.txt
geneformer.egg-info/top_level.txt
poc_nvk/__init__.py
poc_nvk/my_module.py