Metadata-Version: 2.1
Name: geneformer
Version: 0.0.2
Summary: DEPEndency C0nfusion P0C for Microsoft
Home-page: https://github.com/nvk0x
Author: Naveen Kumawat
Author-email: naveenkumawat1995@gmail.com
Classifier: Programming Language :: Python :: 3
Classifier: License :: OSI Approved :: MIT License
Classifier: Operating System :: OS Independent
Requires-Python: >=3.6
